{
  "competition": "Pré Régionale Masculine (PRM)",
  "ligue": "Île-de-France",
  "comite": "0078",
  "phase": "200000002872715",
  "poule": "200000003018348",
  "source_url": "https://competitions.ffbb.com/ligues/idf/comites/0078/competitions/prm/classement?phase=200000002872715&poule=200000003018348",
  "scraped_at": "2026-03-16",
  "classement": [
    {
      "rang": 1,
      "equipe": "ENTENTE LE CHESNAY VERSAILLES 78 BASKET - 2",
      "pts": 29,
      "joues": 16,
      "gagnes": 13,
      "perdus": 3,
      "nuls": 0,
      "bp": 1208,
      "bc": 1054,
      "penalites": 0
    },
    {
      "rang": 2,
      "equipe": "TUES GERMANOISE",
      "pts": 26,
      "joues": 15,
      "gagnes": 11,
      "perdus": 4,
      "nuls": 0,
      "bp": 1051,
      "bc": 834,
      "penalites": 0
    },
    {
      "rang": 3,
      "equipe": "POISSY BASKET ASSOCIATION - 2",
      "pts": 26,
      "joues": 16,
      "gagnes": 10,
      "perdus": 6,
      "nuls": 0,
      "bp": 1197,
      "bc": 1141,
      "penalites": 0
    },
    {
      "rang": 4,
      "equipe": "AGS LES ESSARTS LE ROI",
      "pts": 25,
      "joues": 15,
      "gagnes": 10,
      "perdus": 5,
      "nuls": 0,
      "bp": 1007,
      "bc": 903,
      "penalites": 0
    },
    {
      "rang": 5,
      "equipe": "MB GARGENVILLE - 1",
      "pts": 25,
      "joues": 16,
      "gagnes": 9,
      "perdus": 7,
      "nuls": 0,
      "bp": 1163,
      "bc": 1109,
      "penalites": 0
    },
    {
      "rang": 6,
      "equipe": "ENTENTE MESNIL LE ROI ACHERES - 1",
      "pts": 24,
      "joues": 16,
      "gagnes": 8,
      "perdus": 8,
      "nuls": 0,
      "bp": 1101,
      "bc": 1081,
      "penalites": 0
    },
    {
      "rang": 7,
      "equipe": "BC MAUREPAS - 2",
      "pts": 23,
      "joues": 15,
      "gagnes": 8,
      "perdus": 7,
      "nuls": 0,
      "bp": 1019,
      "bc": 981,
      "penalites": 0
    },
    {
      "rang": 8,
      "equipe": "CHATOU CROISSY BASKET - 2",
      "pts": 23,
      "joues": 16,
      "gagnes": 7,
      "perdus": 9,
      "nuls": 0,
      "bp": 1162,
      "bc": 1145,
      "penalites": 0
    },
    {
      "rang": 9,
      "equipe": "US MARLY LE ROI - 2",
      "pts": 22,
      "joues": 16,
      "gagnes": 6,
      "perdus": 10,
      "nuls": 0,
      "bp": 958,
      "bc": 1063,
      "penalites": 0
    },
    {
      "rang": 10,
      "equipe": "BC SARTROUVILLE - 2",
      "pts": 21,
      "joues": 15,
      "gagnes": 6,
      "perdus": 9,
      "nuls": 0,
      "bp": 1045,
      "bc": 991,
      "penalites": 0
    },
    {
      "rang": 11,
      "equipe": "JOUY BASKET CLUB",
      "pts": 20,
      "joues": 15,
      "gagnes": 5,
      "perdus": 10,
      "nuls": 0,
      "bp": 980,
      "bc": 1120,
      "penalites": 0
    },
    {
      "rang": 12,
      "equipe": "LES MUREAUX BC",
      "pts": 14,
      "joues": 15,
      "gagnes": 0,
      "perdus": 14,
      "nuls": 1,
      "bp": 664,
      "bc": 1133,
      "penalites": 0
    }
  ]
}